LICENSE
MANIFEST.in
README.rst
setup.cfg
setup.py
git_lint.egg-info/PKG-INFO
git_lint.egg-info/SOURCES.txt
git_lint.egg-info/dependency_links.txt
git_lint.egg-info/requires.txt
git_lint.egg-info/top_level.txt
gitlint/__init__.py
gitlint/git.py
gitlint/hg.py
gitlint/linters.py
gitlint/utils.py
gitlint/version.py
gitlint/configs/checkstyle.xml
gitlint/configs/coffeelint.json
gitlint/configs/config.yaml
gitlint/configs/jshint.json
gitlint/configs/pylintrc
scripts/git-lint
scripts/pre-commit.git-lint.sh
scripts/pre-commit.hg-lint.sh
scripts/custom_linters/ini_linter.py
scripts/custom_linters/jpegtran-linter.sh
scripts/custom_linters/optipng-linter.sh
scripts/custom_linters/pngcrush-linter.sh
scripts/custom_linters/tidy-wrapper.sh
test/e2etest/__init__.py
test/e2etest/test_e2e.py
test/unittest/__init__.py
test/unittest/test_git.py
test/unittest/test_gitlint.py
test/unittest/test_hg.py
test/unittest/test_linters.py
test/unittest/test_utils.py